{
    "categoryAxis": {
        "axisColor": "#DADADA",
        "gridAlpha": 0.07,
        "minPeriod": "7DD",
        "parseDates": "true",
        "startOnAxis": "true",
        "twoLineMode": "true"
    },
    "categoryField": "item",
    "chartCursor": {
        "cursorPosition": "mouse"
    },
    "chartScrollbar": {
        "autoGridCount": "true",
        "graph": "g_reg",
        "scrollbarHeight": 40
    },
    "dataProvider": [
        {
            "assignment_unique": 0,
            "forum_combined_unique": 0,
            "forum_comment_unique": 0,
            "forum_post_unique": 0,
            "item": "2013-09-25",
            "lecture_combined_unique": 0,
            "lecture_download_unique": 0,
            "lecture_view_unique": 0,
            "quiz_exam_unique": 0,
            "quiz_homework_unique": 0,
            "quiz_quiz_unique": 0,
            "quiz_survey_unique": 0,
            "quiz_video_unique": 0,
            "registrations": 1,
            "work_combined_unique": 0
        },
        {
            "assignment_unique": 0,
            "forum_combined_unique": 0,
            "forum_comment_unique": 0,
            "forum_post_unique": 0,
            "item": "2013-09-30",
            "lecture_combined_unique": 0,
            "lecture_download_unique": 0,
            "lecture_view_unique": 0,
            "quiz_exam_unique": 0,
            "quiz_homework_unique": 0,
            "quiz_quiz_unique": 0,
            "quiz_survey_unique": 0,
            "quiz_video_unique": 0,
            "registrations": 226,
            "work_combined_unique": 0
        },
        {
            "assignment_unique": 0,
            "forum_combined_unique": 0,
            "forum_comment_unique": 0,
            "forum_post_unique": 0,
            "item": "2013-10-06",
            "lecture_combined_unique": 0,
            "lecture_download_unique": 0,
            "lecture_view_unique": 0,
            "quiz_exam_unique": 0,
            "quiz_homework_unique": 0,
            "quiz_quiz_unique": 0,
            "quiz_survey_unique": 0,
            "quiz_video_unique": 0,
            "registrations": 458,
            "work_combined_unique": 0
        },
        {
            "assignment_unique": 0,
            "forum_combined_unique": 0,
            "forum_comment_unique": 0,
            "forum_post_unique": 0,
            "item": "2013-10-13",
            "lecture_combined_unique": 0,
            "lecture_download_unique": 0,
            "lecture_view_unique": 0,
            "quiz_exam_unique": 0,
            "quiz_homework_unique": 0,
            "quiz_quiz_unique": 0,
            "quiz_survey_unique": 0,
            "quiz_video_unique": 0,
            "registrations": 717,
            "work_combined_unique": 0
        },
        {
            "assignment_unique": 0,
            "forum_combined_unique": 0,
            "forum_comment_unique": 0,
            "forum_post_unique": 0,
            "item": "2013-10-20",
            "lecture_combined_unique": 0,
            "lecture_download_unique": 0,
            "lecture_view_unique": 0,
            "quiz_exam_unique": 0,
            "quiz_homework_unique": 0,
            "quiz_quiz_unique": 0,
            "quiz_survey_unique": 0,
            "quiz_video_unique": 0,
            "registrations": 1183,
            "work_combined_unique": 0
        },
        {
            "assignment_unique": 0,
            "forum_combined_unique": 0,
            "forum_comment_unique": 0,
            "forum_post_unique": 0,
            "item": "2013-10-27",
            "lecture_combined_unique": 0,
            "lecture_download_unique": 0,
            "lecture_view_unique": 0,
            "quiz_exam_unique": 0,
            "quiz_homework_unique": 0,
            "quiz_quiz_unique": 0,
            "quiz_survey_unique": 0,
            "quiz_video_unique": 0,
            "registrations": 1584,
            "work_combined_unique": 0
        },
        {
            "assignment_unique": 0,
            "forum_combined_unique": 0,
            "forum_comment_unique": 0,
            "forum_post_unique": 0,
            "item": "2013-11-03",
            "lecture_combined_unique": 0,
            "lecture_download_unique": 0,
            "lecture_view_unique": 0,
            "quiz_exam_unique": 0,
            "quiz_homework_unique": 0,
            "quiz_quiz_unique": 0,
            "quiz_survey_unique": 0,
            "quiz_video_unique": 0,
            "registrations": 1893,
            "work_combined_unique": 0
        },
        {
            "assignment_unique": 0,
            "forum_combined_unique": 0,
            "forum_comment_unique": 0,
            "forum_post_unique": 0,
            "item": "2013-11-10",
            "lecture_combined_unique": 0,
            "lecture_download_unique": 0,
            "lecture_view_unique": 0,
            "quiz_exam_unique": 0,
            "quiz_homework_unique": 0,
            "quiz_quiz_unique": 0,
            "quiz_survey_unique": 0,
            "quiz_video_unique": 0,
            "registrations": 2137,
            "work_combined_unique": 0
        },
        {
            "assignment_unique": 0,
            "forum_combined_unique": 0,
            "forum_comment_unique": 0,
            "forum_post_unique": 0,
            "item": "2013-11-17",
            "lecture_combined_unique": 0,
            "lecture_download_unique": 0,
            "lecture_view_unique": 0,
            "quiz_exam_unique": 0,
            "quiz_homework_unique": 0,
            "quiz_quiz_unique": 0,
            "quiz_survey_unique": 0,
            "quiz_video_unique": 0,
            "registrations": 2369,
            "work_combined_unique": 0
        },
        {
            "assignment_unique": 0,
            "forum_combined_unique": 0,
            "forum_comment_unique": 0,
            "forum_post_unique": 0,
            "item": "2013-11-24",
            "lecture_combined_unique": 0,
            "lecture_download_unique": 0,
            "lecture_view_unique": 0,
            "quiz_exam_unique": 0,
            "quiz_homework_unique": 0,
            "quiz_quiz_unique": 0,
            "quiz_survey_unique": 0,
            "quiz_video_unique": 0,
            "registrations": 2599,
            "work_combined_unique": 0
        },
        {
            "assignment_unique": 0,
            "forum_combined_unique": 0,
            "forum_comment_unique": 0,
            "forum_post_unique": 0,
            "item": "2013-12-01",
            "lecture_combined_unique": 0,
            "lecture_download_unique": 0,
            "lecture_view_unique": 0,
            "quiz_exam_unique": 0,
            "quiz_homework_unique": 0,
            "quiz_quiz_unique": 0,
            "quiz_survey_unique": 0,
            "quiz_video_unique": 0,
            "registrations": 2803,
            "work_combined_unique": 0
        },
        {
            "assignment_unique": 0,
            "forum_combined_unique": 0,
            "forum_comment_unique": 0,
            "forum_post_unique": 0,
            "item": "2013-12-08",
            "lecture_combined_unique": 0,
            "lecture_download_unique": 0,
            "lecture_view_unique": 0,
            "quiz_exam_unique": 0,
            "quiz_homework_unique": 0,
            "quiz_quiz_unique": 0,
            "quiz_survey_unique": 0,
            "quiz_video_unique": 0,
            "registrations": 3019,
            "work_combined_unique": 0
        },
        {
            "assignment_unique": 0,
            "forum_combined_unique": 0,
            "forum_comment_unique": 0,
            "forum_post_unique": 0,
            "item": "2013-12-15",
            "lecture_combined_unique": 0,
            "lecture_download_unique": 0,
            "lecture_view_unique": 0,
            "quiz_exam_unique": 0,
            "quiz_homework_unique": 0,
            "quiz_quiz_unique": 0,
            "quiz_survey_unique": 0,
            "quiz_video_unique": 0,
            "registrations": 3251,
            "work_combined_unique": 0
        },
        {
            "assignment_unique": 0,
            "forum_combined_unique": 0,
            "forum_comment_unique": 0,
            "forum_post_unique": 0,
            "item": "2013-12-22",
            "lecture_combined_unique": 0,
            "lecture_download_unique": 0,
            "lecture_view_unique": 0,
            "quiz_exam_unique": 0,
            "quiz_homework_unique": 0,
            "quiz_quiz_unique": 0,
            "quiz_survey_unique": 0,
            "quiz_video_unique": 0,
            "registrations": 3388,
            "work_combined_unique": 0
        },
        {
            "assignment_unique": 0,
            "forum_combined_unique": 0,
            "forum_comment_unique": 0,
            "forum_post_unique": 0,
            "item": "2013-12-29",
            "lecture_combined_unique": 0,
            "lecture_download_unique": 0,
            "lecture_view_unique": 0,
            "quiz_exam_unique": 0,
            "quiz_homework_unique": 0,
            "quiz_quiz_unique": 0,
            "quiz_survey_unique": 0,
            "quiz_video_unique": 0,
            "registrations": 3591,
            "work_combined_unique": 0
        },
        {
            "assignment_unique": 0,
            "forum_combined_unique": 0,
            "forum_comment_unique": 0,
            "forum_post_unique": 0,
            "item": "2014-01-05",
            "lecture_combined_unique": 0,
            "lecture_download_unique": 0,
            "lecture_view_unique": 0,
            "quiz_exam_unique": 0,
            "quiz_homework_unique": 0,
            "quiz_quiz_unique": 0,
            "quiz_survey_unique": 0,
            "quiz_video_unique": 0,
            "registrations": 3827,
            "work_combined_unique": 0
        },
        {
            "assignment_unique": 0,
            "forum_combined_unique": 0,
            "forum_comment_unique": 0,
            "forum_post_unique": 0,
            "item": "2014-01-12",
            "lecture_combined_unique": 0,
            "lecture_download_unique": 0,
            "lecture_view_unique": 0,
            "quiz_exam_unique": 0,
            "quiz_homework_unique": 0,
            "quiz_quiz_unique": 0,
            "quiz_survey_unique": 0,
            "quiz_video_unique": 0,
            "registrations": 4125,
            "work_combined_unique": 0
        },
        {
            "assignment_unique": 0,
            "forum_combined_unique": 0,
            "forum_comment_unique": 0,
            "forum_post_unique": 0,
            "item": "2014-01-19",
            "lecture_combined_unique": 0,
            "lecture_download_unique": 0,
            "lecture_view_unique": 0,
            "quiz_exam_unique": 0,
            "quiz_homework_unique": 0,
            "quiz_quiz_unique": 0,
            "quiz_survey_unique": 0,
            "quiz_video_unique": 0,
            "registrations": 4531,
            "work_combined_unique": 0
        },
        {
            "assignment_unique": 0,
            "forum_combined_unique": 0,
            "forum_comment_unique": 0,
            "forum_post_unique": 0,
            "item": "2014-01-26",
            "lecture_combined_unique": 0,
            "lecture_download_unique": 0,
            "lecture_view_unique": 0,
            "quiz_exam_unique": 0,
            "quiz_homework_unique": 0,
            "quiz_quiz_unique": 0,
            "quiz_survey_unique": 0,
            "quiz_video_unique": 0,
            "registrations": 4870,
            "work_combined_unique": 0
        },
        {
            "assignment_unique": 0,
            "forum_combined_unique": 0,
            "forum_comment_unique": 0,
            "forum_post_unique": 0,
            "item": "2014-02-02",
            "lecture_combined_unique": 0,
            "lecture_download_unique": 0,
            "lecture_view_unique": 0,
            "quiz_exam_unique": 0,
            "quiz_homework_unique": 0,
            "quiz_quiz_unique": 0,
            "quiz_survey_unique": 0,
            "quiz_video_unique": 0,
            "registrations": 5281,
            "work_combined_unique": 0
        },
        {
            "assignment_unique": 0,
            "forum_combined_unique": 0,
            "forum_comment_unique": 0,
            "forum_post_unique": 0,
            "item": "2014-02-09",
            "lecture_combined_unique": 0,
            "lecture_download_unique": 0,
            "lecture_view_unique": 0,
            "quiz_exam_unique": 0,
            "quiz_homework_unique": 0,
            "quiz_quiz_unique": 0,
            "quiz_survey_unique": 0,
            "quiz_video_unique": 0,
            "registrations": 5883,
            "work_combined_unique": 0
        },
        {
            "assignment_unique": 0,
            "forum_combined_unique": 208,
            "forum_comment_unique": 55,
            "forum_post_unique": 197,
            "item": "2014-02-16",
            "lecture_combined_unique": 2345,
            "lecture_download_unique": 885,
            "lecture_view_unique": 2106,
            "quiz_exam_unique": 0,
            "quiz_homework_unique": 0,
            "quiz_quiz_unique": 0,
            "quiz_survey_unique": 979,
            "quiz_video_unique": 0,
            "registrations": 6723,
            "work_combined_unique": 0
        },
        {
            "assignment_unique": 0,
            "forum_combined_unique": 121,
            "forum_comment_unique": 38,
            "forum_post_unique": 106,
            "item": "2014-02-23",
            "lecture_combined_unique": 2276,
            "lecture_download_unique": 956,
            "lecture_view_unique": 1904,
            "quiz_exam_unique": 0,
            "quiz_homework_unique": 0,
            "quiz_quiz_unique": 652,
            "quiz_survey_unique": 379,
            "quiz_video_unique": 0,
            "registrations": 7337,
            "work_combined_unique": 652
        },
        {
            "assignment_unique": 0,
            "forum_combined_unique": 80,
            "forum_comment_unique": 29,
            "forum_post_unique": 67,
            "item": "2014-03-02",
            "lecture_combined_unique": 1636,
            "lecture_download_unique": 714,
            "lecture_view_unique": 1264,
            "quiz_exam_unique": 0,
            "quiz_homework_unique": 0,
            "quiz_quiz_unique": 1064,
            "quiz_survey_unique": 164,
            "quiz_video_unique": 0,
            "registrations": 7646,
            "work_combined_unique": 1064
        },
        {
            "assignment_unique": 0,
            "forum_combined_unique": 88,
            "forum_comment_unique": 30,
            "forum_post_unique": 76,
            "item": "2014-03-09",
            "lecture_combined_unique": 1670,
            "lecture_download_unique": 747,
            "lecture_view_unique": 1275,
            "quiz_exam_unique": 0,
            "quiz_homework_unique": 0,
            "quiz_quiz_unique": 940,
            "quiz_survey_unique": 71,
            "quiz_video_unique": 0,
            "registrations": 7814,
            "work_combined_unique": 940
        },
        {
            "assignment_unique": 0,
            "forum_combined_unique": 68,
            "forum_comment_unique": 20,
            "forum_post_unique": 60,
            "item": "2014-03-16",
            "lecture_combined_unique": 1326,
            "lecture_download_unique": 645,
            "lecture_view_unique": 929,
            "quiz_exam_unique": 0,
            "quiz_homework_unique": 0,
            "quiz_quiz_unique": 686,
            "quiz_survey_unique": 20,
            "quiz_video_unique": 0,
            "registrations": 7959,
            "work_combined_unique": 686
        },
        {
            "assignment_unique": 0,
            "forum_combined_unique": 57,
            "forum_comment_unique": 17,
            "forum_post_unique": 46,
            "item": "2014-03-23",
            "lecture_combined_unique": 1178,
            "lecture_download_unique": 572,
            "lecture_view_unique": 816,
            "quiz_exam_unique": 0,
            "quiz_homework_unique": 0,
            "quiz_quiz_unique": 573,
            "quiz_survey_unique": 17,
            "quiz_video_unique": 0,
            "registrations": 8072,
            "work_combined_unique": 573
        },
        {
            "assignment_unique": 0,
            "forum_combined_unique": 65,
            "forum_comment_unique": 11,
            "forum_post_unique": 59,
            "item": "2014-03-30",
            "lecture_combined_unique": 971,
            "lecture_download_unique": 430,
            "lecture_view_unique": 701,
            "quiz_exam_unique": 0,
            "quiz_homework_unique": 0,
            "quiz_quiz_unique": 655,
            "quiz_survey_unique": 12,
            "quiz_video_unique": 0,
            "registrations": 8194,
            "work_combined_unique": 655
        },
        {
            "assignment_unique": 0,
            "forum_combined_unique": 41,
            "forum_comment_unique": 11,
            "forum_post_unique": 34,
            "item": "2014-04-06",
            "lecture_combined_unique": 767,
            "lecture_download_unique": 384,
            "lecture_view_unique": 508,
            "quiz_exam_unique": 0,
            "quiz_homework_unique": 0,
            "quiz_quiz_unique": 322,
            "quiz_survey_unique": 5,
            "quiz_video_unique": 0,
            "registrations": 8290,
            "work_combined_unique": 322
        },
        {
            "assignment_unique": 0,
            "forum_combined_unique": 39,
            "forum_comment_unique": 12,
            "forum_post_unique": 35,
            "item": "2014-04-13",
            "lecture_combined_unique": 748,
            "lecture_download_unique": 376,
            "lecture_view_unique": 501,
            "quiz_exam_unique": 0,
            "quiz_homework_unique": 0,
            "quiz_quiz_unique": 269,
            "quiz_survey_unique": 6,
            "quiz_video_unique": 0,
            "registrations": 8373,
            "work_combined_unique": 269
        },
        {
            "assignment_unique": 0,
            "forum_combined_unique": 22,
            "forum_comment_unique": 5,
            "forum_post_unique": 20,
            "item": "2014-04-20",
            "lecture_combined_unique": 574,
            "lecture_download_unique": 234,
            "lecture_view_unique": 410,
            "quiz_exam_unique": 0,
            "quiz_homework_unique": 0,
            "quiz_quiz_unique": 372,
            "quiz_survey_unique": 7,
            "quiz_video_unique": 0,
            "registrations": 8482,
            "work_combined_unique": 372
        },
        {
            "assignment_unique": 0,
            "forum_combined_unique": 32,
            "forum_comment_unique": 14,
            "forum_post_unique": 25,
            "item": "2014-04-27",
            "lecture_combined_unique": 733,
            "lecture_download_unique": 334,
            "lecture_view_unique": 514,
            "quiz_exam_unique": 0,
            "quiz_homework_unique": 0,
            "quiz_quiz_unique": 322,
            "quiz_survey_unique": 8,
            "quiz_video_unique": 0,
            "registrations": 8627,
            "work_combined_unique": 322
        },
        {
            "assignment_unique": 0,
            "forum_combined_unique": 36,
            "forum_comment_unique": 11,
            "forum_post_unique": 34,
            "item": "2014-05-04",
            "lecture_combined_unique": 781,
            "lecture_download_unique": 392,
            "lecture_view_unique": 521,
            "quiz_exam_unique": 0,
            "quiz_homework_unique": 0,
            "quiz_quiz_unique": 517,
            "quiz_survey_unique": 10,
            "quiz_video_unique": 0,
            "registrations": 8750,
            "work_combined_unique": 517
        },
        {
            "assignment_unique": 0,
            "forum_combined_unique": 51,
            "forum_comment_unique": 7,
            "forum_post_unique": 47,
            "item": "2014-05-11",
            "lecture_combined_unique": 767,
            "lecture_download_unique": 415,
            "lecture_view_unique": 492,
            "quiz_exam_unique": 0,
            "quiz_homework_unique": 0,
            "quiz_quiz_unique": 411,
            "quiz_survey_unique": 3,
            "quiz_video_unique": 0,
            "registrations": 8858,
            "work_combined_unique": 411
        },
        {
            "assignment_unique": 0,
            "forum_combined_unique": 19,
            "forum_comment_unique": 1,
            "forum_post_unique": 18,
            "item": "2014-05-18",
            "lecture_combined_unique": 420,
            "lecture_download_unique": 192,
            "lecture_view_unique": 282,
            "quiz_exam_unique": 0,
            "quiz_homework_unique": 0,
            "quiz_quiz_unique": 228,
            "quiz_survey_unique": 3,
            "quiz_video_unique": 0,
            "registrations": 8973,
            "work_combined_unique": 228
        },
        {
            "assignment_unique": 0,
            "forum_combined_unique": 6,
            "forum_comment_unique": 1,
            "forum_post_unique": 6,
            "item": "2014-05-25",
            "lecture_combined_unique": 170,
            "lecture_download_unique": 70,
            "lecture_view_unique": 114,
            "quiz_exam_unique": 0,
            "quiz_homework_unique": 0,
            "quiz_quiz_unique": 28,
            "quiz_survey_unique": 5,
            "quiz_video_unique": 0,
            "registrations": 9053,
            "work_combined_unique": 28
        },
        {
            "assignment_unique": 0,
            "forum_combined_unique": 4,
            "forum_comment_unique": 0,
            "forum_post_unique": 4,
            "item": "2014-06-01",
            "lecture_combined_unique": 136,
            "lecture_download_unique": 49,
            "lecture_view_unique": 101,
            "quiz_exam_unique": 0,
            "quiz_homework_unique": 0,
            "quiz_quiz_unique": 15,
            "quiz_survey_unique": 4,
            "quiz_video_unique": 0,
            "registrations": 9137,
            "work_combined_unique": 15
        },
        {
            "assignment_unique": 0,
            "forum_combined_unique": 13,
            "forum_comment_unique": 0,
            "forum_post_unique": 13,
            "item": "2014-06-08",
            "lecture_combined_unique": 143,
            "lecture_download_unique": 56,
            "lecture_view_unique": 101,
            "quiz_exam_unique": 0,
            "quiz_homework_unique": 0,
            "quiz_quiz_unique": 7,
            "quiz_survey_unique": 56,
            "quiz_video_unique": 0,
            "registrations": 9221,
            "work_combined_unique": 7
        },
        {
            "assignment_unique": 0,
            "forum_combined_unique": 5,
            "forum_comment_unique": 0,
            "forum_post_unique": 5,
            "item": "2014-06-15",
            "lecture_combined_unique": 107,
            "lecture_download_unique": 36,
            "lecture_view_unique": 82,
            "quiz_exam_unique": 0,
            "quiz_homework_unique": 0,
            "quiz_quiz_unique": 5,
            "quiz_survey_unique": 18,
            "quiz_video_unique": 0,
            "registrations": 9293,
            "work_combined_unique": 5
        },
        {
            "assignment_unique": 0,
            "forum_combined_unique": 2,
            "forum_comment_unique": 0,
            "forum_post_unique": 2,
            "item": "2014-06-22",
            "lecture_combined_unique": 68,
            "lecture_download_unique": 22,
            "lecture_view_unique": 53,
            "quiz_exam_unique": 0,
            "quiz_homework_unique": 0,
            "quiz_quiz_unique": 3,
            "quiz_survey_unique": 2,
            "quiz_video_unique": 0,
            "registrations": 9320,
            "work_combined_unique": 3
        },
        {
            "assignment_unique": 0,
            "forum_combined_unique": 1,
            "forum_comment_unique": 0,
            "forum_post_unique": 1,
            "item": "2014-06-29",
            "lecture_combined_unique": 35,
            "lecture_download_unique": 9,
            "lecture_view_unique": 28,
            "quiz_exam_unique": 0,
            "quiz_homework_unique": 0,
            "quiz_quiz_unique": 2,
            "quiz_survey_unique": 1,
            "quiz_video_unique": 0,
            "registrations": 9325,
            "work_combined_unique": 2
        },
        {
            "assignment_unique": 0,
            "forum_combined_unique": 0,
            "forum_comment_unique": 0,
            "forum_post_unique": 0,
            "item": "2014-07-06",
            "lecture_combined_unique": 39,
            "lecture_download_unique": 17,
            "lecture_view_unique": 28,
            "quiz_exam_unique": 0,
            "quiz_homework_unique": 0,
            "quiz_quiz_unique": 0,
            "quiz_survey_unique": 1,
            "quiz_video_unique": 0,
            "registrations": 9325,
            "work_combined_unique": 0
        },
        {
            "assignment_unique": 0,
            "forum_combined_unique": 0,
            "forum_comment_unique": 0,
            "forum_post_unique": 0,
            "item": "2014-07-13",
            "lecture_combined_unique": 33,
            "lecture_download_unique": 8,
            "lecture_view_unique": 27,
            "quiz_exam_unique": 0,
            "quiz_homework_unique": 0,
            "quiz_quiz_unique": 0,
            "quiz_survey_unique": 1,
            "quiz_video_unique": 0,
            "registrations": 9325,
            "work_combined_unique": 0
        },
        {
            "assignment_unique": 0,
            "forum_combined_unique": 0,
            "forum_comment_unique": 0,
            "forum_post_unique": 0,
            "item": "2014-07-20",
            "lecture_combined_unique": 33,
            "lecture_download_unique": 6,
            "lecture_view_unique": 28,
            "quiz_exam_unique": 0,
            "quiz_homework_unique": 0,
            "quiz_quiz_unique": 1,
            "quiz_survey_unique": 0,
            "quiz_video_unique": 0,
            "registrations": 9325,
            "work_combined_unique": 1
        },
        {
            "assignment_unique": 0,
            "forum_combined_unique": 0,
            "forum_comment_unique": 0,
            "forum_post_unique": 0,
            "item": "2014-07-27",
            "lecture_combined_unique": 25,
            "lecture_download_unique": 7,
            "lecture_view_unique": 21,
            "quiz_exam_unique": 0,
            "quiz_homework_unique": 0,
            "quiz_quiz_unique": 1,
            "quiz_survey_unique": 0,
            "quiz_video_unique": 0,
            "registrations": 9325,
            "work_combined_unique": 1
        },
        {
            "assignment_unique": 0,
            "forum_combined_unique": 0,
            "forum_comment_unique": 0,
            "forum_post_unique": 0,
            "item": "2014-08-03",
            "lecture_combined_unique": 24,
            "lecture_download_unique": 5,
            "lecture_view_unique": 21,
            "quiz_exam_unique": 0,
            "quiz_homework_unique": 0,
            "quiz_quiz_unique": 0,
            "quiz_survey_unique": 0,
            "quiz_video_unique": 0,
            "registrations": 9325,
            "work_combined_unique": 0
        },
        {
            "assignment_unique": 0,
            "forum_combined_unique": 0,
            "forum_comment_unique": 0,
            "forum_post_unique": 0,
            "item": "2014-08-10",
            "lecture_combined_unique": 18,
            "lecture_download_unique": 4,
            "lecture_view_unique": 15,
            "quiz_exam_unique": 0,
            "quiz_homework_unique": 0,
            "quiz_quiz_unique": 0,
            "quiz_survey_unique": 0,
            "quiz_video_unique": 0,
            "registrations": 9325,
            "work_combined_unique": 0
        },
        {
            "assignment_unique": 0,
            "forum_combined_unique": 0,
            "forum_comment_unique": 0,
            "forum_post_unique": 0,
            "item": "2014-08-17",
            "lecture_combined_unique": 19,
            "lecture_download_unique": 3,
            "lecture_view_unique": 17,
            "quiz_exam_unique": 0,
            "quiz_homework_unique": 0,
            "quiz_quiz_unique": 1,
            "quiz_survey_unique": 0,
            "quiz_video_unique": 0,
            "registrations": 9325,
            "work_combined_unique": 1
        },
        {
            "assignment_unique": 0,
            "forum_combined_unique": 0,
            "forum_comment_unique": 0,
            "forum_post_unique": 0,
            "item": "2014-08-24",
            "lecture_combined_unique": 27,
            "lecture_download_unique": 6,
            "lecture_view_unique": 22,
            "quiz_exam_unique": 0,
            "quiz_homework_unique": 0,
            "quiz_quiz_unique": 1,
            "quiz_survey_unique": 0,
            "quiz_video_unique": 0,
            "registrations": 9325,
            "work_combined_unique": 1
        },
        {
            "assignment_unique": 0,
            "forum_combined_unique": 0,
            "forum_comment_unique": 0,
            "forum_post_unique": 0,
            "item": "2014-08-31",
            "lecture_combined_unique": 16,
            "lecture_download_unique": 0,
            "lecture_view_unique": 16,
            "quiz_exam_unique": 0,
            "quiz_homework_unique": 0,
            "quiz_quiz_unique": 0,
            "quiz_survey_unique": 0,
            "quiz_video_unique": 0,
            "registrations": 9325,
            "work_combined_unique": 0
        },
        {
            "assignment_unique": 0,
            "forum_combined_unique": 0,
            "forum_comment_unique": 0,
            "forum_post_unique": 0,
            "item": "2014-09-07",
            "lecture_combined_unique": 14,
            "lecture_download_unique": 5,
            "lecture_view_unique": 11,
            "quiz_exam_unique": 0,
            "quiz_homework_unique": 0,
            "quiz_quiz_unique": 0,
            "quiz_survey_unique": 0,
            "quiz_video_unique": 0,
            "registrations": 9325,
            "work_combined_unique": 0
        },
        {
            "assignment_unique": 0,
            "forum_combined_unique": 0,
            "forum_comment_unique": 0,
            "forum_post_unique": 0,
            "item": "2014-09-14",
            "lecture_combined_unique": 14,
            "lecture_download_unique": 5,
            "lecture_view_unique": 10,
            "quiz_exam_unique": 0,
            "quiz_homework_unique": 0,
            "quiz_quiz_unique": 0,
            "quiz_survey_unique": 0,
            "quiz_video_unique": 0,
            "registrations": 9325,
            "work_combined_unique": 0
        },
        {
            "assignment_unique": 0,
            "forum_combined_unique": 0,
            "forum_comment_unique": 0,
            "forum_post_unique": 0,
            "item": "2014-09-21",
            "lecture_combined_unique": 14,
            "lecture_download_unique": 3,
            "lecture_view_unique": 12,
            "quiz_exam_unique": 0,
            "quiz_homework_unique": 0,
            "quiz_quiz_unique": 2,
            "quiz_survey_unique": 0,
            "quiz_video_unique": 0,
            "registrations": 9325,
            "work_combined_unique": 2
        },
        {
            "assignment_unique": 0,
            "forum_combined_unique": 0,
            "forum_comment_unique": 0,
            "forum_post_unique": 0,
            "item": "2014-09-28",
            "lecture_combined_unique": 15,
            "lecture_download_unique": 6,
            "lecture_view_unique": 12,
            "quiz_exam_unique": 0,
            "quiz_homework_unique": 0,
            "quiz_quiz_unique": 1,
            "quiz_survey_unique": 0,
            "quiz_video_unique": 0,
            "registrations": 9325,
            "work_combined_unique": 1
        },
        {
            "assignment_unique": 0,
            "forum_combined_unique": 0,
            "forum_comment_unique": 0,
            "forum_post_unique": 0,
            "item": "2014-10-05",
            "lecture_combined_unique": 2,
            "lecture_download_unique": 2,
            "lecture_view_unique": 1,
            "quiz_exam_unique": 0,
            "quiz_homework_unique": 0,
            "quiz_quiz_unique": 0,
            "quiz_survey_unique": 0,
            "quiz_video_unique": 0,
            "registrations": 9325,
            "work_combined_unique": 0
        }
    ],
    "graphs": [
        {
            "balloonText": "<span style='font-size:10px; color:#000000;'><b>[[title]]: [[value]]</b></span>",
            "fillAlphas": 0.6,
            "id": "g_reg",
            "lineAlpha": 0.4,
            "stackable": "false",
            "title": "registrations",
            "type": "column",
            "valueField": "registrations"
        },
        {
            "balloonText": "<span style='font-size:10px; color:#000000;'><b>[[title]]: [[value]]</b></span>",
            "fillAlphas": 0.6,
            "lineAlpha": 0.4,
            "stackable": "false",
            "title": "assignment_unique",
            "type": "column",
            "valueField": "assignment_unique"
        },
        {
            "balloonText": "<span style='font-size:10px; color:#000000;'><b>[[title]]: [[value]]</b></span>",
            "fillAlphas": 0.6,
            "lineAlpha": 0.4,
            "stackable": "false",
            "title": "forum_combined_unique",
            "type": "column",
            "valueField": "forum_combined_unique"
        },
        {
            "balloonText": "<span style='font-size:10px; color:#000000;'><b>[[title]]: [[value]]</b></span>",
            "fillAlphas": 0.6,
            "lineAlpha": 0.4,
            "stackable": "false",
            "title": "forum_comment_unique",
            "type": "column",
            "valueField": "forum_comment_unique"
        },
        {
            "balloonText": "<span style='font-size:10px; color:#000000;'><b>[[title]]: [[value]]</b></span>",
            "fillAlphas": 0.6,
            "lineAlpha": 0.4,
            "stackable": "false",
            "title": "forum_post_unique",
            "type": "column",
            "valueField": "forum_post_unique"
        },
        {
            "balloonText": "<span style='font-size:10px; color:#000000;'><b>[[title]]: [[value]]</b></span>",
            "fillAlphas": 0.6,
            "lineAlpha": 0.4,
            "stackable": "false",
            "title": "lecture_combined_unique",
            "type": "column",
            "valueField": "lecture_combined_unique"
        },
        {
            "balloonText": "<span style='font-size:10px; color:#000000;'><b>[[title]]: [[value]]</b></span>",
            "fillAlphas": 0.6,
            "lineAlpha": 0.4,
            "stackable": "false",
            "title": "lecture_download_unique",
            "type": "column",
            "valueField": "lecture_download_unique"
        },
        {
            "balloonText": "<span style='font-size:10px; color:#000000;'><b>[[title]]: [[value]]</b></span>",
            "fillAlphas": 0.6,
            "lineAlpha": 0.4,
            "stackable": "false",
            "title": "lecture_view_unique",
            "type": "column",
            "valueField": "lecture_view_unique"
        },
        {
            "balloonText": "<span style='font-size:10px; color:#000000;'><b>[[title]]: [[value]]</b></span>",
            "fillAlphas": 0.6,
            "lineAlpha": 0.4,
            "stackable": "false",
            "title": "quiz_exam_unique",
            "type": "column",
            "valueField": "quiz_exam_unique"
        },
        {
            "balloonText": "<span style='font-size:10px; color:#000000;'><b>[[title]]: [[value]]</b></span>",
            "fillAlphas": 0.6,
            "lineAlpha": 0.4,
            "stackable": "false",
            "title": "quiz_homework_unique",
            "type": "column",
            "valueField": "quiz_homework_unique"
        },
        {
            "balloonText": "<span style='font-size:10px; color:#000000;'><b>[[title]]: [[value]]</b></span>",
            "fillAlphas": 0.6,
            "lineAlpha": 0.4,
            "stackable": "false",
            "title": "quiz_quiz_unique",
            "type": "column",
            "valueField": "quiz_quiz_unique"
        },
        {
            "balloonText": "<span style='font-size:10px; color:#000000;'><b>[[title]]: [[value]]</b></span>",
            "fillAlphas": 0.6,
            "lineAlpha": 0.4,
            "stackable": "false",
            "title": "quiz_survey_unique",
            "type": "column",
            "valueField": "quiz_survey_unique"
        },
        {
            "balloonText": "<span style='font-size:10px; color:#000000;'><b>[[title]]: [[value]]</b></span>",
            "fillAlphas": 0.6,
            "lineAlpha": 0.4,
            "stackable": "false",
            "title": "quiz_video_unique",
            "type": "column",
            "valueField": "quiz_video_unique"
        },
        {
            "balloonText": "<span style='font-size:10px; color:#000000;'><b>[[title]]: [[value]]</b></span>",
            "fillAlphas": 0.6,
            "lineAlpha": 0.4,
            "stackable": "false",
            "title": "work_combined_unique",
            "type": "column",
            "valueField": "work_combined_unique"
        }
    ],
    "legend": {
        "equalWidths": "false",
        "periodValueText": "total: [[value.sum]]",
        "position": "left",
        "valueAlign": "left",
        "valueWidth": 100
    },
    "marginBottom": 0,
    "marginLeft": 0,
    "marginTop": 10,
    "mouseWheelZoomEnabled": "true",
    "pathToImages": "http://www.amcharts.com/lib/3/images/",
    "plotAreaBorderAlpha": 0,
    "theme": "none",
    "type": "serial",
    "valueAxes": [
        {
            "gridAlpha": 0.07,
            "position": "left",
            "stackType": "regular",
            "title": "villesafricaines-001"
        }
    ]
}