{
    "categoryAxis": {
        "axisColor": "#DADADA",
        "gridAlpha": 0.07,
        "parseDates": "true",
        "startOnAxis": "true",
        "twoLineMode": "true"
    },
    "categoryField": "item",
    "chartCursor": {
        "cursorAlpha": 0
    },
    "chartScrollbar": {},
    "dataProvider": [
        {
            "assignment_unique": 0,
            "forum_combined_unique": 0,
            "forum_comment_unique": 0,
            "forum_post_unique": 0,
            "item": "2014-05-10",
            "lecture_combined_unique": 0,
            "lecture_download_unique": 0,
            "lecture_view_unique": 0,
            "quiz_exam_unique": 0,
            "quiz_homework_unique": 0,
            "quiz_quiz_unique": 0,
            "quiz_survey_unique": 0,
            "quiz_video_unique": 0,
            "registrations": 1,
            "work_combined_unique": 0
        },
        {
            "assignment_unique": 0,
            "forum_combined_unique": 0,
            "forum_comment_unique": 0,
            "forum_post_unique": 0,
            "item": "2014-05-14",
            "lecture_combined_unique": 0,
            "lecture_download_unique": 0,
            "lecture_view_unique": 0,
            "quiz_exam_unique": 0,
            "quiz_homework_unique": 0,
            "quiz_quiz_unique": 0,
            "quiz_survey_unique": 0,
            "quiz_video_unique": 0,
            "registrations": 138,
            "work_combined_unique": 0
        },
        {
            "assignment_unique": 0,
            "forum_combined_unique": 0,
            "forum_comment_unique": 0,
            "forum_post_unique": 0,
            "item": "2014-05-18",
            "lecture_combined_unique": 0,
            "lecture_download_unique": 0,
            "lecture_view_unique": 0,
            "quiz_exam_unique": 0,
            "quiz_homework_unique": 0,
            "quiz_quiz_unique": 0,
            "quiz_survey_unique": 0,
            "quiz_video_unique": 0,
            "registrations": 123,
            "work_combined_unique": 0
        },
        {
            "assignment_unique": 0,
            "forum_combined_unique": 0,
            "forum_comment_unique": 0,
            "forum_post_unique": 0,
            "item": "2014-05-25",
            "lecture_combined_unique": 0,
            "lecture_download_unique": 0,
            "lecture_view_unique": 0,
            "quiz_exam_unique": 0,
            "quiz_homework_unique": 0,
            "quiz_quiz_unique": 0,
            "quiz_survey_unique": 0,
            "quiz_video_unique": 0,
            "registrations": 78,
            "work_combined_unique": 0
        },
        {
            "assignment_unique": 0,
            "forum_combined_unique": 0,
            "forum_comment_unique": 0,
            "forum_post_unique": 0,
            "item": "2014-06-01",
            "lecture_combined_unique": 0,
            "lecture_download_unique": 0,
            "lecture_view_unique": 0,
            "quiz_exam_unique": 0,
            "quiz_homework_unique": 0,
            "quiz_quiz_unique": 0,
            "quiz_survey_unique": 0,
            "quiz_video_unique": 0,
            "registrations": 89,
            "work_combined_unique": 0
        },
        {
            "assignment_unique": 0,
            "forum_combined_unique": 0,
            "forum_comment_unique": 0,
            "forum_post_unique": 0,
            "item": "2014-06-08",
            "lecture_combined_unique": 0,
            "lecture_download_unique": 0,
            "lecture_view_unique": 0,
            "quiz_exam_unique": 0,
            "quiz_homework_unique": 0,
            "quiz_quiz_unique": 0,
            "quiz_survey_unique": 0,
            "quiz_video_unique": 0,
            "registrations": 184,
            "work_combined_unique": 0
        },
        {
            "assignment_unique": 0,
            "forum_combined_unique": 0,
            "forum_comment_unique": 0,
            "forum_post_unique": 0,
            "item": "2014-06-15",
            "lecture_combined_unique": 0,
            "lecture_download_unique": 0,
            "lecture_view_unique": 0,
            "quiz_exam_unique": 0,
            "quiz_homework_unique": 0,
            "quiz_quiz_unique": 0,
            "quiz_survey_unique": 0,
            "quiz_video_unique": 0,
            "registrations": 96,
            "work_combined_unique": 0
        },
        {
            "assignment_unique": 0,
            "forum_combined_unique": 0,
            "forum_comment_unique": 0,
            "forum_post_unique": 0,
            "item": "2014-06-22",
            "lecture_combined_unique": 0,
            "lecture_download_unique": 0,
            "lecture_view_unique": 0,
            "quiz_exam_unique": 0,
            "quiz_homework_unique": 0,
            "quiz_quiz_unique": 0,
            "quiz_survey_unique": 0,
            "quiz_video_unique": 0,
            "registrations": 164,
            "work_combined_unique": 0
        },
        {
            "assignment_unique": 0,
            "forum_combined_unique": 0,
            "forum_comment_unique": 0,
            "forum_post_unique": 0,
            "item": "2014-06-29",
            "lecture_combined_unique": 0,
            "lecture_download_unique": 0,
            "lecture_view_unique": 0,
            "quiz_exam_unique": 0,
            "quiz_homework_unique": 0,
            "quiz_quiz_unique": 0,
            "quiz_survey_unique": 0,
            "quiz_video_unique": 0,
            "registrations": 175,
            "work_combined_unique": 0
        },
        {
            "assignment_unique": 0,
            "forum_combined_unique": 0,
            "forum_comment_unique": 0,
            "forum_post_unique": 0,
            "item": "2014-07-06",
            "lecture_combined_unique": 0,
            "lecture_download_unique": 0,
            "lecture_view_unique": 0,
            "quiz_exam_unique": 0,
            "quiz_homework_unique": 0,
            "quiz_quiz_unique": 0,
            "quiz_survey_unique": 0,
            "quiz_video_unique": 0,
            "registrations": 134,
            "work_combined_unique": 0
        },
        {
            "assignment_unique": 0,
            "forum_combined_unique": 0,
            "forum_comment_unique": 0,
            "forum_post_unique": 0,
            "item": "2014-07-13",
            "lecture_combined_unique": 0,
            "lecture_download_unique": 0,
            "lecture_view_unique": 0,
            "quiz_exam_unique": 0,
            "quiz_homework_unique": 0,
            "quiz_quiz_unique": 0,
            "quiz_survey_unique": 0,
            "quiz_video_unique": 0,
            "registrations": 139,
            "work_combined_unique": 0
        },
        {
            "assignment_unique": 0,
            "forum_combined_unique": 0,
            "forum_comment_unique": 0,
            "forum_post_unique": 0,
            "item": "2014-07-20",
            "lecture_combined_unique": 0,
            "lecture_download_unique": 0,
            "lecture_view_unique": 0,
            "quiz_exam_unique": 0,
            "quiz_homework_unique": 0,
            "quiz_quiz_unique": 0,
            "quiz_survey_unique": 0,
            "quiz_video_unique": 0,
            "registrations": 138,
            "work_combined_unique": 0
        },
        {
            "assignment_unique": 0,
            "forum_combined_unique": 0,
            "forum_comment_unique": 0,
            "forum_post_unique": 0,
            "item": "2014-07-27",
            "lecture_combined_unique": 0,
            "lecture_download_unique": 0,
            "lecture_view_unique": 0,
            "quiz_exam_unique": 0,
            "quiz_homework_unique": 0,
            "quiz_quiz_unique": 0,
            "quiz_survey_unique": 0,
            "quiz_video_unique": 0,
            "registrations": 141,
            "work_combined_unique": 0
        },
        {
            "assignment_unique": 0,
            "forum_combined_unique": 0,
            "forum_comment_unique": 0,
            "forum_post_unique": 0,
            "item": "2014-08-03",
            "lecture_combined_unique": 0,
            "lecture_download_unique": 0,
            "lecture_view_unique": 0,
            "quiz_exam_unique": 0,
            "quiz_homework_unique": 0,
            "quiz_quiz_unique": 0,
            "quiz_survey_unique": 0,
            "quiz_video_unique": 0,
            "registrations": 163,
            "work_combined_unique": 0
        },
        {
            "assignment_unique": 0,
            "forum_combined_unique": 0,
            "forum_comment_unique": 0,
            "forum_post_unique": 0,
            "item": "2014-08-10",
            "lecture_combined_unique": 0,
            "lecture_download_unique": 0,
            "lecture_view_unique": 0,
            "quiz_exam_unique": 0,
            "quiz_homework_unique": 0,
            "quiz_quiz_unique": 0,
            "quiz_survey_unique": 0,
            "quiz_video_unique": 0,
            "registrations": 179,
            "work_combined_unique": 0
        },
        {
            "assignment_unique": 0,
            "forum_combined_unique": 0,
            "forum_comment_unique": 0,
            "forum_post_unique": 0,
            "item": "2014-08-17",
            "lecture_combined_unique": 0,
            "lecture_download_unique": 0,
            "lecture_view_unique": 0,
            "quiz_exam_unique": 0,
            "quiz_homework_unique": 0,
            "quiz_quiz_unique": 0,
            "quiz_survey_unique": 0,
            "quiz_video_unique": 0,
            "registrations": 168,
            "work_combined_unique": 0
        },
        {
            "assignment_unique": 0,
            "forum_combined_unique": 0,
            "forum_comment_unique": 0,
            "forum_post_unique": 0,
            "item": "2014-08-24",
            "lecture_combined_unique": 0,
            "lecture_download_unique": 0,
            "lecture_view_unique": 0,
            "quiz_exam_unique": 0,
            "quiz_homework_unique": 0,
            "quiz_quiz_unique": 0,
            "quiz_survey_unique": 0,
            "quiz_video_unique": 0,
            "registrations": 244,
            "work_combined_unique": 0
        },
        {
            "assignment_unique": 0,
            "forum_combined_unique": 0,
            "forum_comment_unique": 0,
            "forum_post_unique": 0,
            "item": "2014-08-31",
            "lecture_combined_unique": 0,
            "lecture_download_unique": 0,
            "lecture_view_unique": 0,
            "quiz_exam_unique": 0,
            "quiz_homework_unique": 0,
            "quiz_quiz_unique": 0,
            "quiz_survey_unique": 0,
            "quiz_video_unique": 0,
            "registrations": 207,
            "work_combined_unique": 0
        },
        {
            "assignment_unique": 0,
            "forum_combined_unique": 0,
            "forum_comment_unique": 0,
            "forum_post_unique": 0,
            "item": "2014-09-07",
            "lecture_combined_unique": 0,
            "lecture_download_unique": 0,
            "lecture_view_unique": 0,
            "quiz_exam_unique": 0,
            "quiz_homework_unique": 0,
            "quiz_quiz_unique": 0,
            "quiz_survey_unique": 0,
            "quiz_video_unique": 0,
            "registrations": 234,
            "work_combined_unique": 0
        },
        {
            "assignment_unique": 0,
            "forum_combined_unique": 0,
            "forum_comment_unique": 0,
            "forum_post_unique": 0,
            "item": "2014-09-14",
            "lecture_combined_unique": 0,
            "lecture_download_unique": 0,
            "lecture_view_unique": 0,
            "quiz_exam_unique": 0,
            "quiz_homework_unique": 0,
            "quiz_quiz_unique": 0,
            "quiz_survey_unique": 0,
            "quiz_video_unique": 0,
            "registrations": 168,
            "work_combined_unique": 0
        },
        {
            "assignment_unique": 0,
            "forum_combined_unique": 0,
            "forum_comment_unique": 0,
            "forum_post_unique": 0,
            "item": "2014-09-21",
            "lecture_combined_unique": 0,
            "lecture_download_unique": 0,
            "lecture_view_unique": 0,
            "quiz_exam_unique": 0,
            "quiz_homework_unique": 0,
            "quiz_quiz_unique": 0,
            "quiz_survey_unique": 0,
            "quiz_video_unique": 0,
            "registrations": 189,
            "work_combined_unique": 0
        },
        {
            "assignment_unique": 0,
            "forum_combined_unique": 0,
            "forum_comment_unique": 0,
            "forum_post_unique": 0,
            "item": "2014-09-28",
            "lecture_combined_unique": 0,
            "lecture_download_unique": 0,
            "lecture_view_unique": 0,
            "quiz_exam_unique": 0,
            "quiz_homework_unique": 0,
            "quiz_quiz_unique": 0,
            "quiz_survey_unique": 0,
            "quiz_video_unique": 0,
            "registrations": 223,
            "work_combined_unique": 0
        },
        {
            "assignment_unique": 0,
            "forum_combined_unique": 0,
            "forum_comment_unique": 0,
            "forum_post_unique": 0,
            "item": "2014-10-05",
            "lecture_combined_unique": 0,
            "lecture_download_unique": 0,
            "lecture_view_unique": 0,
            "quiz_exam_unique": 0,
            "quiz_homework_unique": 0,
            "quiz_quiz_unique": 0,
            "quiz_survey_unique": 0,
            "quiz_video_unique": 0,
            "registrations": 61,
            "work_combined_unique": 0
        }
    ],
    "graphs": [
        {
            "balloonText": "<span style='font-size:10px; color:#000000;'><b>[[title]]: [[value]]</b></span>",
            "fillAlphas": 0.6,
            "lineAlpha": 0.4,
            "title": "registrations",
            "valueField": "registrations"
        },
        {
            "balloonText": "<span style='font-size:10px; color:#000000;'><b>[[title]]: [[value]]</b></span>",
            "fillAlphas": 0.6,
            "lineAlpha": 0.4,
            "title": "assignment_unique",
            "valueField": "assignment_unique"
        },
        {
            "balloonText": "<span style='font-size:10px; color:#000000;'><b>[[title]]: [[value]]</b></span>",
            "fillAlphas": 0.6,
            "lineAlpha": 0.4,
            "title": "forum_combined_unique",
            "valueField": "forum_combined_unique"
        },
        {
            "balloonText": "<span style='font-size:10px; color:#000000;'><b>[[title]]: [[value]]</b></span>",
            "fillAlphas": 0.6,
            "lineAlpha": 0.4,
            "title": "forum_comment_unique",
            "valueField": "forum_comment_unique"
        },
        {
            "balloonText": "<span style='font-size:10px; color:#000000;'><b>[[title]]: [[value]]</b></span>",
            "fillAlphas": 0.6,
            "lineAlpha": 0.4,
            "title": "forum_post_unique",
            "valueField": "forum_post_unique"
        },
        {
            "balloonText": "<span style='font-size:10px; color:#000000;'><b>[[title]]: [[value]]</b></span>",
            "fillAlphas": 0.6,
            "lineAlpha": 0.4,
            "title": "lecture_combined_unique",
            "valueField": "lecture_combined_unique"
        },
        {
            "balloonText": "<span style='font-size:10px; color:#000000;'><b>[[title]]: [[value]]</b></span>",
            "fillAlphas": 0.6,
            "lineAlpha": 0.4,
            "title": "lecture_download_unique",
            "valueField": "lecture_download_unique"
        },
        {
            "balloonText": "<span style='font-size:10px; color:#000000;'><b>[[title]]: [[value]]</b></span>",
            "fillAlphas": 0.6,
            "lineAlpha": 0.4,
            "title": "lecture_view_unique",
            "valueField": "lecture_view_unique"
        },
        {
            "balloonText": "<span style='font-size:10px; color:#000000;'><b>[[title]]: [[value]]</b></span>",
            "fillAlphas": 0.6,
            "lineAlpha": 0.4,
            "title": "quiz_exam_unique",
            "valueField": "quiz_exam_unique"
        },
        {
            "balloonText": "<span style='font-size:10px; color:#000000;'><b>[[title]]: [[value]]</b></span>",
            "fillAlphas": 0.6,
            "lineAlpha": 0.4,
            "title": "quiz_homework_unique",
            "valueField": "quiz_homework_unique"
        },
        {
            "balloonText": "<span style='font-size:10px; color:#000000;'><b>[[title]]: [[value]]</b></span>",
            "fillAlphas": 0.6,
            "lineAlpha": 0.4,
            "title": "quiz_quiz_unique",
            "valueField": "quiz_quiz_unique"
        },
        {
            "balloonText": "<span style='font-size:10px; color:#000000;'><b>[[title]]: [[value]]</b></span>",
            "fillAlphas": 0.6,
            "lineAlpha": 0.4,
            "title": "quiz_survey_unique",
            "valueField": "quiz_survey_unique"
        },
        {
            "balloonText": "<span style='font-size:10px; color:#000000;'><b>[[title]]: [[value]]</b></span>",
            "fillAlphas": 0.6,
            "lineAlpha": 0.4,
            "title": "quiz_video_unique",
            "valueField": "quiz_video_unique"
        },
        {
            "balloonText": "<span style='font-size:10px; color:#000000;'><b>[[title]]: [[value]]</b></span>",
            "fillAlphas": 0.6,
            "lineAlpha": 0.4,
            "title": "work_combined_unique",
            "valueField": "work_combined_unique"
        }
    ],
    "legend": {
        "equalWidths": "false",
        "periodValueText": "total: [[value.sum]]",
        "position": "left",
        "valueAlign": "left",
        "valueWidth": 100
    },
    "marginBottom": 0,
    "marginLeft": 0,
    "marginTop": 10,
    "pathToImages": "http://www.amcharts.com/lib/3/images/",
    "plotAreaBorderAlpha": 0,
    "theme": "none",
    "type": "serial",
    "valueAxes": [
        {
            "gridAlpha": 0.07,
            "position": "left",
            "stackType": "regular",
            "title": "villesafricaines-002"
        }
    ]
}